qiwi_kassa/__init__.py
qiwi_kassa/actions.py
qiwi_kassa/admin.py
qiwi_kassa/apps.py
qiwi_kassa/models.py
qiwi_kassa/signals.py
qiwi_kassa/tests.py
qiwi_kassa/urls.py
qiwi_kassa/views.py
django_qiwi_kassa-0.2.dist-info/METADATA
django_qiwi_kassa-0.2.dist-info/WHEEL
django_qiwi_kassa-0.2.dist-info/top_level.txt
django_qiwi_kassa-0.2.dist-info/RECORD
